{
	"entries" : 
	[
		{
			"name" : "BASIC_Dictionary_BINARY_DIR",
			"properties" : 
			[
				{
					"name" : "HELPSTRING",
					"value" : "Value Computed by CMake"
				}
			],
			"type" : "STATIC",
			"value" : "/Users/lalalalz/CLionProjects/algorithm/cmake-build-debug/BASIC_Dictionary"
		},
		{
			"name" : "BASIC_Dictionary_IS_TOP_LEVEL",
			"properties" : 
			[
				{
					"name" : "HELPSTRING",
					"value" : "Value Computed by CMake"
				}
			],
			"type" : "STATIC",
			"value" : "OFF"
		},
		{
			"name" : "BASIC_Dictionary_SOURCE_DIR",
			"properties" : 
			[
				{
					"name" : "HELPSTRING",
					"value" : "Value Computed by CMake"
				}
			],
			"type" : "STATIC",
			"value" : "/Users/lalalalz/CLionProjects/algorithm/BASIC_Dictionary"
		},
		{
			"name" : "BASIC_사전_BINARY_DIR",
			"properties" : 
			[
				{
					"name" : "HELPSTRING",
					"value" : "Value Computed by CMake"
				}
			],
			"type" : "STATIC",
			"value" : "/Users/lalalalz/CLionProjects/algorithm/cmake-build-debug/BASIC_사전"
		},
		{
			"name" : "BASIC_사전_IS_TOP_LEVEL",
			"properties" : 
			[
				{
					"name" : "HELPSTRING",
					"value" : "Value Computed by CMake"
				}
			],
			"type" : "STATIC",
			"value" : "OFF"
		},
		{
			"name" : "BASIC_사전_SOURCE_DIR",
			"properties" : 
			[
				{
					"name" : "HELPSTRING",
					"value" : "Value Computed by CMake"
				}
			],
			"type" : "STATIC",
			"value" : "/Users/lalalalz/CLionProjects/algorithm/BASIC_사전"
		},
		{
			"name" : "CMAKE_ADDR2LINE",
			"properties" : 
			[
				{
					"name" : "ADVANCED",
					"value" : "1"
				},
				{
					"name" : "HELPSTRING",
					"value" : "Path to a program."
				}
			],
			"type" : "FILEPATH",
			"value" : "CMAKE_ADDR2LINE-NOTFOUND"
		},
		{
			"name" : "CMAKE_AR",
			"properties" : 
			[
				{
					"name" : "ADVANCED",
					"value" : "1"
				},
				{
					"name" : "HELPSTRING",
					"value" : "Path to a program."
				}
			],
			"type" : "FILEPATH",
			"value" : "/Library/Developer/CommandLineTools/usr/bin/ar"
		},
		{
			"name" : "CMAKE_BUILD_TYPE",
			"properties" : 
			[
				{
					"name" : "HELPSTRING",
					"value" : "Choose the type of build, options are: None Debug Release RelWithDebInfo MinSizeRel ..."
				}
			],
			"type" : "STRING",
			"value" : "Debug"
		},
		{
			"name" : "CMAKE_CACHEFILE_DIR",
			"properties" : 
			[
				{
					"name" : "HELPSTRING",
					"value" : "This is the directory where this CMakeCache.txt was created"
				}
			],
			"type" : "INTERNAL",
			"value" : "/Users/lalalalz/CLionProjects/algorithm/cmake-build-debug"
		},
		{
			"name" : "CMAKE_CACHE_MAJOR_VERSION",
			"properties" : 
			[
				{
					"name" : "HELPSTRING",
					"value" : "Major version of cmake used to create the current loaded cache"
				}
			],
			"type" : "INTERNAL",
			"value" : "3"
		},
		{
			"name" : "CMAKE_CACHE_MINOR_VERSION",
			"properties" : 
			[
				{
					"name" : "HELPSTRING",
					"value" : "Minor version of cmake used to create the current loaded cache"
				}
			],
			"type" : "INTERNAL",
			"value" : "21"
		},
		{
			"name" : "CMAKE_CACHE_PATCH_VERSION",
			"properties" : 
			[
				{
					"name" : "HELPSTRING",
					"value" : "Patch version of cmake used to create the current loaded cache"
				}
			],
			"type" : "INTERNAL",
			"value" : "1"
		},
		{
			"name" : "CMAKE_COMMAND",
			"properties" : 
			[
				{
					"name" : "HELPSTRING",
					"value" : "Path to CMake executable."
				}
			],
			"type" : "INTERNAL",
			"value" : "/Applications/CLion.app/Contents/bin/cmake/mac/bin/cmake"
		},
		{
			"name" : "CMAKE_CPACK_COMMAND",
			"properties" : 
			[
				{
					"name" : "HELPSTRING",
					"value" : "Path to cpack program executable."
				}
			],
			"type" : "INTERNAL",
			"value" : "/Applications/CLion.app/Contents/bin/cmake/mac/bin/cpack"
		},
		{
			"name" : "CMAKE_CTEST_COMMAND",
			"properties" : 
			[
				{
					"name" : "HELPSTRING",
					"value" : "Path to ctest program executable."
				}
			],
			"type" : "INTERNAL",
			"value" : "/Applications/CLion.app/Contents/bin/cmake/mac/bin/ctest"
		},
		{
			"name" : "CMAKE_CXX_COMPILER",
			"properties" : 
			[
				{
					"name" : "ADVANCED",
					"value" : "1"
				},
				{
					"name" : "HELPSTRING",
					"value" : "CXX compiler"
				}
			],
			"type" : "FILEPATH",
			"value" : "/Library/Developer/CommandLineTools/usr/bin/c++"
		},
		{
			"name" : "CMAKE_CXX_FLAGS",
			"properties" : 
			[
				{
					"name" : "ADVANCED",
					"value" : "1"
				},
				{
					"name" : "HELPSTRING",
					"value" : "Flags used by the CXX compiler during all build types."
				}
			],
			"type" : "STRING",
			"value" : ""
		},
		{
			"name" : "CMAKE_CXX_FLAGS_DEBUG",
			"properties" : 
			[
				{
					"name" : "ADVANCED",
					"value" : "1"
				},
				{
					"name" : "HELPSTRING",
					"value" : "Flags used by the CXX compiler during DEBUG builds."
				}
			],
			"type" : "STRING",
			"value" : "-g"
		},
		{
			"name" : "CMAKE_CXX_FLAGS_MINSIZEREL",
			"properties" : 
			[
				{
					"name" : "ADVANCED",
					"value" : "1"
				},
				{
					"name" : "HELPSTRING",
					"value" : "Flags used by the CXX compiler during MINSIZEREL builds."
				}
			],
			"type" : "STRING",
			"value" : "-Os -DNDEBUG"
		},
		{
			"name" : "CMAKE_CXX_FLAGS_RELEASE",
			"properties" : 
			[
				{
					"name" : "ADVANCED",
					"value" : "1"
				},
				{
					"name" : "HELPSTRING",
					"value" : "Flags used by the CXX compiler during RELEASE builds."
				}
			],
			"type" : "STRING",
			"value" : "-O3 -DNDEBUG"
		},
		{
			"name" : "CMAKE_CXX_FLAGS_RELWITHDEBINFO",
			"properties" : 
			[
				{
					"name" : "ADVANCED",
					"value" : "1"
				},
				{
					"name" : "HELPSTRING",
					"value" : "Flags used by the CXX compiler during RELWITHDEBINFO builds."
				}
			],
			"type" : "STRING",
			"value" : "-O2 -g -DNDEBUG"
		},
		{
			"name" : "CMAKE_C_COMPILER",
			"properties" : 
			[
				{
					"name" : "ADVANCED",
					"value" : "1"
				},
				{
					"name" : "HELPSTRING",
					"value" : "C compiler"
				}
			],
			"type" : "FILEPATH",
			"value" : "/Library/Developer/CommandLineTools/usr/bin/cc"
		},
		{
			"name" : "CMAKE_C_FLAGS",
			"properties" : 
			[
				{
					"name" : "ADVANCED",
					"value" : "1"
				},
				{
					"name" : "HELPSTRING",
					"value" : "Flags used by the C compiler during all build types."
				}
			],
			"type" : "STRING",
			"value" : ""
		},
		{
			"name" : "CMAKE_C_FLAGS_DEBUG",
			"properties" : 
			[
				{
					"name" : "ADVANCED",
					"value" : "1"
				},
				{
					"name" : "HELPSTRING",
					"value" : "Flags used by the C compiler during DEBUG builds."
				}
			],
			"type" : "STRING",
			"value" : "-g"
		},
		{
			"name" : "CMAKE_C_FLAGS_MINSIZEREL",
			"properties" : 
			[
				{
					"name" : "ADVANCED",
					"value" : "1"
				},
				{
					"name" : "HELPSTRING",
					"value" : "Flags used by the C compiler during MINSIZEREL builds."
				}
			],
			"type" : "STRING",
			"value" : "-Os -DNDEBUG"
		},
		{
			"name" : "CMAKE_C_FLAGS_RELEASE",
			"properties" : 
			[
				{
					"name" : "ADVANCED",
					"value" : "1"
				},
				{
					"name" : "HELPSTRING",
					"value" : "Flags used by the C compiler during RELEASE builds."
				}
			],
			"type" : "STRING",
			"value" : "-O3 -DNDEBUG"
		},
		{
			"name" : "CMAKE_C_FLAGS_RELWITHDEBINFO",
			"properties" : 
			[
				{
					"name" : "ADVANCED",
					"value" : "1"
				},
				{
					"name" : "HELPSTRING",
					"value" : "Flags used by the C compiler during RELWITHDEBINFO builds."
				}
			],
			"type" : "STRING",
			"value" : "-O2 -g -DNDEBUG"
		},
		{
			"name" : "CMAKE_DLLTOOL",
			"properties" : 
			[
				{
					"name" : "ADVANCED",
					"value" : "1"
				},
				{
					"name" : "HELPSTRING",
					"value" : "Path to a program."
				}
			],
			"type" : "FILEPATH",
			"value" : "CMAKE_DLLTOOL-NOTFOUND"
		},
		{
			"name" : "CMAKE_EXECUTABLE_FORMAT",
			"properties" : 
			[
				{
					"name" : "HELPSTRING",
					"value" : "Executable file format"
				}
			],
			"type" : "INTERNAL",
			"value" : "MACHO"
		},
		{
			"name" : "CMAKE_EXE_LINKER_FLAGS",
			"properties" : 
			[
				{
					"name" : "ADVANCED",
					"value" : "1"
				},
				{
					"name" : "HELPSTRING",
					"value" : "Flags used by the linker during all build types."
				}
			],
			"type" : "STRING",
			"value" : ""
		},
		{
			"name" : "CMAKE_EXE_LINKER_FLAGS_DEBUG",
			"properties" : 
			[
				{
					"name" : "ADVANCED",
					"value" : "1"
				},
				{
					"name" : "HELPSTRING",
					"value" : "Flags used by the linker during DEBUG builds."
				}
			],
			"type" : "STRING",
			"value" : ""
		},
		{
			"name" : "CMAKE_EXE_LINKER_FLAGS_MINSIZEREL",
			"properties" : 
			[
				{
					"name" : "ADVANCED",
					"value" : "1"
				},
				{
					"name" : "HELPSTRING",
					"value" : "Flags used by the linker during MINSIZEREL builds."
				}
			],
			"type" : "STRING",
			"value" : ""
		},
		{
			"name" : "CMAKE_EXE_LINKER_FLAGS_RELEASE",
			"properties" : 
			[
				{
					"name" : "ADVANCED",
					"value" : "1"
				},
				{
					"name" : "HELPSTRING",
					"value" : "Flags used by the linker during RELEASE builds."
				}
			],
			"type" : "STRING",
			"value" : ""
		},
		{
			"name" : "CMAKE_EXE_LINKER_FLAGS_RELWITHDEBINFO",
			"properties" : 
			[
				{
					"name" : "ADVANCED",
					"value" : "1"
				},
				{
					"name" : "HELPSTRING",
					"value" : "Flags used by the linker during RELWITHDEBINFO builds."
				}
			],
			"type" : "STRING",
			"value" : ""
		},
		{
			"name" : "CMAKE_EXPORT_COMPILE_COMMANDS",
			"properties" : 
			[
				{
					"name" : "ADVANCED",
					"value" : "1"
				},
				{
					"name" : "HELPSTRING",
					"value" : "Enable/Disable output of compile commands during generation."
				}
			],
			"type" : "BOOL",
			"value" : ""
		},
		{
			"name" : "CMAKE_EXTRA_GENERATOR",
			"properties" : 
			[
				{
					"name" : "HELPSTRING",
					"value" : "Name of external makefile project generator."
				}
			],
			"type" : "INTERNAL",
			"value" : ""
		},
		{
			"name" : "CMAKE_GENERATOR",
			"properties" : 
			[
				{
					"name" : "HELPSTRING",
					"value" : "Name of generator."
				}
			],
			"type" : "INTERNAL",
			"value" : "Ninja"
		},
		{
			"name" : "CMAKE_GENERATOR_INSTANCE",
			"properties" : 
			[
				{
					"name" : "HELPSTRING",
					"value" : "Generator instance identifier."
				}
			],
			"type" : "INTERNAL",
			"value" : ""
		},
		{
			"name" : "CMAKE_GENERATOR_PLATFORM",
			"properties" : 
			[
				{
					"name" : "HELPSTRING",
					"value" : "Name of generator platform."
				}
			],
			"type" : "INTERNAL",
			"value" : ""
		},
		{
			"name" : "CMAKE_GENERATOR_TOOLSET",
			"properties" : 
			[
				{
					"name" : "HELPSTRING",
					"value" : "Name of generator toolset."
				}
			],
			"type" : "INTERNAL",
			"value" : ""
		},
		{
			"name" : "CMAKE_HOME_DIRECTORY",
			"properties" : 
			[
				{
					"name" : "HELPSTRING",
					"value" : "Source directory with the top level CMakeLists.txt file for this project"
				}
			],
			"type" : "INTERNAL",
			"value" : "/Users/lalalalz/CLionProjects/algorithm"
		},
		{
			"name" : "CMAKE_INSTALL_NAME_TOOL",
			"properties" : 
			[
				{
					"name" : "ADVANCED",
					"value" : "1"
				},
				{
					"name" : "HELPSTRING",
					"value" : "Path to a program."
				}
			],
			"type" : "FILEPATH",
			"value" : "/usr/bin/install_name_tool"
		},
		{
			"name" : "CMAKE_INSTALL_PREFIX",
			"properties" : 
			[
				{
					"name" : "HELPSTRING",
					"value" : "Install path prefix, prepended onto install directories."
				}
			],
			"type" : "PATH",
			"value" : "/usr/local"
		},
		{
			"name" : "CMAKE_LINKER",
			"properties" : 
			[
				{
					"name" : "ADVANCED",
					"value" : "1"
				},
				{
					"name" : "HELPSTRING",
					"value" : "Path to a program."
				}
			],
			"type" : "FILEPATH",
			"value" : "/Library/Developer/CommandLineTools/usr/bin/ld"
		},
		{
			"name" : "CMAKE_MAKE_PROGRAM",
			"properties" : 
			[
				{
					"name" : "HELPSTRING",
					"value" : "No help, variable specified on the command line."
				}
			],
			"type" : "UNINITIALIZED",
			"value" : "/Applications/CLion.app/Contents/bin/ninja/mac/ninja"
		},
		{
			"name" : "CMAKE_MODULE_LINKER_FLAGS",
			"properties" : 
			[
				{
					"name" : "ADVANCED",
					"value" : "1"
				},
				{
					"name" : "HELPSTRING",
					"value" : "Flags used by the linker during the creation of modules during all build types."
				}
			],
			"type" : "STRING",
			"value" : ""
		},
		{
			"name" : "CMAKE_MODULE_LINKER_FLAGS_DEBUG",
			"properties" : 
			[
				{
					"name" : "ADVANCED",
					"value" : "1"
				},
				{
					"name" : "HELPSTRING",
					"value" : "Flags used by the linker during the creation of modules during DEBUG builds."
				}
			],
			"type" : "STRING",
			"value" : ""
		},
		{
			"name" : "CMAKE_MODULE_LINKER_FLAGS_MINSIZEREL",
			"properties" : 
			[
				{
					"name" : "ADVANCED",
					"value" : "1"
				},
				{
					"name" : "HELPSTRING",
					"value" : "Flags used by the linker during the creation of modules during MINSIZEREL builds."
				}
			],
			"type" : "STRING",
			"value" : ""
		},
		{
			"name" : "CMAKE_MODULE_LINKER_FLAGS_RELEASE",
			"properties" : 
			[
				{
					"name" : "ADVANCED",
					"value" : "1"
				},
				{
					"name" : "HELPSTRING",
					"value" : "Flags used by the linker during the creation of modules during RELEASE builds."
				}
			],
			"type" : "STRING",
			"value" : ""
		},
		{
			"name" : "CMAKE_MODULE_LINKER_FLAGS_RELWITHDEBINFO",
			"properties" : 
			[
				{
					"name" : "ADVANCED",
					"value" : "1"
				},
				{
					"name" : "HELPSTRING",
					"value" : "Flags used by the linker during the creation of modules during RELWITHDEBINFO builds."
				}
			],
			"type" : "STRING",
			"value" : ""
		},
		{
			"name" : "CMAKE_NM",
			"properties" : 
			[
				{
					"name" : "ADVANCED",
					"value" : "1"
				},
				{
					"name" : "HELPSTRING",
					"value" : "Path to a program."
				}
			],
			"type" : "FILEPATH",
			"value" : "/Library/Developer/CommandLineTools/usr/bin/nm"
		},
		{
			"name" : "CMAKE_NUMBER_OF_MAKEFILES",
			"properties" : 
			[
				{
					"name" : "HELPSTRING",
					"value" : "number of local generators"
				}
			],
			"type" : "INTERNAL",
			"value" : "52"
		},
		{
			"name" : "CMAKE_OBJCOPY",
			"properties" : 
			[
				{
					"name" : "ADVANCED",
					"value" : "1"
				},
				{
					"name" : "HELPSTRING",
					"value" : "Path to a program."
				}
			],
			"type" : "FILEPATH",
			"value" : "CMAKE_OBJCOPY-NOTFOUND"
		},
		{
			"name" : "CMAKE_OBJDUMP",
			"properties" : 
			[
				{
					"name" : "ADVANCED",
					"value" : "1"
				},
				{
					"name" : "HELPSTRING",
					"value" : "Path to a program."
				}
			],
			"type" : "FILEPATH",
			"value" : "/Library/Developer/CommandLineTools/usr/bin/objdump"
		},
		{
			"name" : "CMAKE_OSX_ARCHITECTURES",
			"properties" : 
			[
				{
					"name" : "HELPSTRING",
					"value" : "Build architectures for OSX"
				}
			],
			"type" : "STRING",
			"value" : ""
		},
		{
			"name" : "CMAKE_OSX_DEPLOYMENT_TARGET",
			"properties" : 
			[
				{
					"name" : "HELPSTRING",
					"value" : "Minimum OS X version to target for deployment (at runtime); newer APIs weak linked. Set to empty string for default value."
				}
			],
			"type" : "STRING",
			"value" : ""
		},
		{
			"name" : "CMAKE_OSX_SYSROOT",
			"properties" : 
			[
				{
					"name" : "HELPSTRING",
					"value" : "The product will be built against the headers and libraries located inside the indicated SDK."
				}
			],
			"type" : "PATH",
			"value" : "/Library/Developer/CommandLineTools/SDKs/MacOSX12.1.sdk"
		},
		{
			"name" : "CMAKE_PLATFORM_INFO_INITIALIZED",
			"properties" : 
			[
				{
					"name" : "HELPSTRING",
					"value" : "Platform information initialized"
				}
			],
			"type" : "INTERNAL",
			"value" : "1"
		},
		{
			"name" : "CMAKE_PROJECT_DESCRIPTION",
			"properties" : 
			[
				{
					"name" : "HELPSTRING",
					"value" : "Value Computed by CMake"
				}
			],
			"type" : "STATIC",
			"value" : ""
		},
		{
			"name" : "CMAKE_PROJECT_HOMEPAGE_URL",
			"properties" : 
			[
				{
					"name" : "HELPSTRING",
					"value" : "Value Computed by CMake"
				}
			],
			"type" : "STATIC",
			"value" : ""
		},
		{
			"name" : "CMAKE_PROJECT_NAME",
			"properties" : 
			[
				{
					"name" : "HELPSTRING",
					"value" : "Value Computed by CMake"
				}
			],
			"type" : "STATIC",
			"value" : "algorithm"
		},
		{
			"name" : "CMAKE_RANLIB",
			"properties" : 
			[
				{
					"name" : "ADVANCED",
					"value" : "1"
				},
				{
					"name" : "HELPSTRING",
					"value" : "Path to a program."
				}
			],
			"type" : "FILEPATH",
			"value" : "/Library/Developer/CommandLineTools/usr/bin/ranlib"
		},
		{
			"name" : "CMAKE_READELF",
			"properties" : 
			[
				{
					"name" : "ADVANCED",
					"value" : "1"
				},
				{
					"name" : "HELPSTRING",
					"value" : "Path to a program."
				}
			],
			"type" : "FILEPATH",
			"value" : "CMAKE_READELF-NOTFOUND"
		},
		{
			"name" : "CMAKE_ROOT",
			"properties" : 
			[
				{
					"name" : "HELPSTRING",
					"value" : "Path to CMake installation."
				}
			],
			"type" : "INTERNAL",
			"value" : "/Applications/CLion.app/Contents/bin/cmake/mac/share/cmake-3.21"
		},
		{
			"name" : "CMAKE_SHARED_LINKER_FLAGS",
			"properties" : 
			[
				{
					"name" : "ADVANCED",
					"value" : "1"
				},
				{
					"name" : "HELPSTRING",
					"value" : "Flags used by the linker during the creation of shared libraries during all build types."
				}
			],
			"type" : "STRING",
			"value" : ""
		},
		{
			"name" : "CMAKE_SHARED_LINKER_FLAGS_DEBUG",
			"properties" : 
			[
				{
					"name" : "ADVANCED",
					"value" : "1"
				},
				{
					"name" : "HELPSTRING",
					"value" : "Flags used by the linker during the creation of shared libraries during DEBUG builds."
				}
			],
			"type" : "STRING",
			"value" : ""
		},
		{
			"name" : "CMAKE_SHARED_LINKER_FLAGS_MINSIZEREL",
			"properties" : 
			[
				{
					"name" : "ADVANCED",
					"value" : "1"
				},
				{
					"name" : "HELPSTRING",
					"value" : "Flags used by the linker during the creation of shared libraries during MINSIZEREL builds."
				}
			],
			"type" : "STRING",
			"value" : ""
		},
		{
			"name" : "CMAKE_SHARED_LINKER_FLAGS_RELEASE",
			"properties" : 
			[
				{
					"name" : "ADVANCED",
					"value" : "1"
				},
				{
					"name" : "HELPSTRING",
					"value" : "Flags used by the linker during the creation of shared libraries during RELEASE builds."
				}
			],
			"type" : "STRING",
			"value" : ""
		},
		{
			"name" : "CMAKE_SHARED_LINKER_FLAGS_RELWITHDEBINFO",
			"properties" : 
			[
				{
					"name" : "ADVANCED",
					"value" : "1"
				},
				{
					"name" : "HELPSTRING",
					"value" : "Flags used by the linker during the creation of shared libraries during RELWITHDEBINFO builds."
				}
			],
			"type" : "STRING",
			"value" : ""
		},
		{
			"name" : "CMAKE_SKIP_INSTALL_RPATH",
			"properties" : 
			[
				{
					"name" : "ADVANCED",
					"value" : "1"
				},
				{
					"name" : "HELPSTRING",
					"value" : "If set, runtime paths are not added when installing shared libraries, but are added when building."
				}
			],
			"type" : "BOOL",
			"value" : "NO"
		},
		{
			"name" : "CMAKE_SKIP_RPATH",
			"properties" : 
			[
				{
					"name" : "ADVANCED",
					"value" : "1"
				},
				{
					"name" : "HELPSTRING",
					"value" : "If set, runtime paths are not added when using shared libraries."
				}
			],
			"type" : "BOOL",
			"value" : "NO"
		},
		{
			"name" : "CMAKE_STATIC_LINKER_FLAGS",
			"properties" : 
			[
				{
					"name" : "ADVANCED",
					"value" : "1"
				},
				{
					"name" : "HELPSTRING",
					"value" : "Flags used by the linker during the creation of static libraries during all build types."
				}
			],
			"type" : "STRING",
			"value" : ""
		},
		{
			"name" : "CMAKE_STATIC_LINKER_FLAGS_DEBUG",
			"properties" : 
			[
				{
					"name" : "ADVANCED",
					"value" : "1"
				},
				{
					"name" : "HELPSTRING",
					"value" : "Flags used by the linker during the creation of static libraries during DEBUG builds."
				}
			],
			"type" : "STRING",
			"value" : ""
		},
		{
			"name" : "CMAKE_STATIC_LINKER_FLAGS_MINSIZEREL",
			"properties" : 
			[
				{
					"name" : "ADVANCED",
					"value" : "1"
				},
				{
					"name" : "HELPSTRING",
					"value" : "Flags used by the linker during the creation of static libraries during MINSIZEREL builds."
				}
			],
			"type" : "STRING",
			"value" : ""
		},
		{
			"name" : "CMAKE_STATIC_LINKER_FLAGS_RELEASE",
			"properties" : 
			[
				{
					"name" : "ADVANCED",
					"value" : "1"
				},
				{
					"name" : "HELPSTRING",
					"value" : "Flags used by the linker during the creation of static libraries during RELEASE builds."
				}
			],
			"type" : "STRING",
			"value" : ""
		},
		{
			"name" : "CMAKE_STATIC_LINKER_FLAGS_RELWITHDEBINFO",
			"properties" : 
			[
				{
					"name" : "ADVANCED",
					"value" : "1"
				},
				{
					"name" : "HELPSTRING",
					"value" : "Flags used by the linker during the creation of static libraries during RELWITHDEBINFO builds."
				}
			],
			"type" : "STRING",
			"value" : ""
		},
		{
			"name" : "CMAKE_STRIP",
			"properties" : 
			[
				{
					"name" : "ADVANCED",
					"value" : "1"
				},
				{
					"name" : "HELPSTRING",
					"value" : "Path to a program."
				}
			],
			"type" : "FILEPATH",
			"value" : "/Library/Developer/CommandLineTools/usr/bin/strip"
		},
		{
			"name" : "CMAKE_UNAME",
			"properties" : 
			[
				{
					"name" : "HELPSTRING",
					"value" : "uname command"
				}
			],
			"type" : "INTERNAL",
			"value" : "/usr/bin/uname"
		},
		{
			"name" : "CMAKE_VERBOSE_MAKEFILE",
			"properties" : 
			[
				{
					"name" : "ADVANCED",
					"value" : "1"
				},
				{
					"name" : "HELPSTRING",
					"value" : "If this value is on, makefiles will be generated without the .SILENT directive, and all commands will be echoed to the console during the make.  This is useful for debugging only. With Visual Studio IDE projects all commands are done without /nologo."
				}
			],
			"type" : "BOOL",
			"value" : "FALSE"
		},
		{
			"name" : "DFS_1_BINARY_DIR",
			"properties" : 
			[
				{
					"name" : "HELPSTRING",
					"value" : "Value Computed by CMake"
				}
			],
			"type" : "STATIC",
			"value" : "/Users/lalalalz/CLionProjects/algorithm/cmake-build-debug/DFS_1"
		},
		{
			"name" : "DFS_1_IS_TOP_LEVEL",
			"properties" : 
			[
				{
					"name" : "HELPSTRING",
					"value" : "Value Computed by CMake"
				}
			],
			"type" : "STATIC",
			"value" : "OFF"
		},
		{
			"name" : "DFS_1_SOURCE_DIR",
			"properties" : 
			[
				{
					"name" : "HELPSTRING",
					"value" : "Value Computed by CMake"
				}
			],
			"type" : "STATIC",
			"value" : "/Users/lalalalz/CLionProjects/algorithm/DFS_1"
		},
		{
			"name" : "DP_1010_BINARY_DIR",
			"properties" : 
			[
				{
					"name" : "HELPSTRING",
					"value" : "Value Computed by CMake"
				}
			],
			"type" : "STATIC",
			"value" : "/Users/lalalalz/CLionProjects/algorithm/cmake-build-debug/DP_1010"
		},
		{
			"name" : "DP_1010_IS_TOP_LEVEL",
			"properties" : 
			[
				{
					"name" : "HELPSTRING",
					"value" : "Value Computed by CMake"
				}
			],
			"type" : "STATIC",
			"value" : "OFF"
		},
		{
			"name" : "DP_1010_SOURCE_DIR",
			"properties" : 
			[
				{
					"name" : "HELPSTRING",
					"value" : "Value Computed by CMake"
				}
			],
			"type" : "STATIC",
			"value" : "/Users/lalalalz/CLionProjects/algorithm/DP_1010"
		},
		{
			"name" : "DP_10844_BINARY_DIR",
			"properties" : 
			[
				{
					"name" : "HELPSTRING",
					"value" : "Value Computed by CMake"
				}
			],
			"type" : "STATIC",
			"value" : "/Users/lalalalz/CLionProjects/algorithm/cmake-build-debug/DP_10844"
		},
		{
			"name" : "DP_10844_IS_TOP_LEVEL",
			"properties" : 
			[
				{
					"name" : "HELPSTRING",
					"value" : "Value Computed by CMake"
				}
			],
			"type" : "STATIC",
			"value" : "OFF"
		},
		{
			"name" : "DP_10844_SOURCE_DIR",
			"properties" : 
			[
				{
					"name" : "HELPSTRING",
					"value" : "Value Computed by CMake"
				}
			],
			"type" : "STATIC",
			"value" : "/Users/lalalalz/CLionProjects/algorithm/DP_10844"
		},
		{
			"name" : "DP_11053_BINARY_DIR",
			"properties" : 
			[
				{
					"name" : "HELPSTRING",
					"value" : "Value Computed by CMake"
				}
			],
			"type" : "STATIC",
			"value" : "/Users/lalalalz/CLionProjects/algorithm/cmake-build-debug/DP_11053"
		},
		{
			"name" : "DP_11053_IS_TOP_LEVEL",
			"properties" : 
			[
				{
					"name" : "HELPSTRING",
					"value" : "Value Computed by CMake"
				}
			],
			"type" : "STATIC",
			"value" : "OFF"
		},
		{
			"name" : "DP_11053_SOURCE_DIR",
			"properties" : 
			[
				{
					"name" : "HELPSTRING",
					"value" : "Value Computed by CMake"
				}
			],
			"type" : "STATIC",
			"value" : "/Users/lalalalz/CLionProjects/algorithm/DP_11053"
		},
		{
			"name" : "DP_1149_BINARY_DIR",
			"properties" : 
			[
				{
					"name" : "HELPSTRING",
					"value" : "Value Computed by CMake"
				}
			],
			"type" : "STATIC",
			"value" : "/Users/lalalalz/CLionProjects/algorithm/cmake-build-debug/DP_1149"
		},
		{
			"name" : "DP_1149_IS_TOP_LEVEL",
			"properties" : 
			[
				{
					"name" : "HELPSTRING",
					"value" : "Value Computed by CMake"
				}
			],
			"type" : "STATIC",
			"value" : "OFF"
		},
		{
			"name" : "DP_1149_SOURCE_DIR",
			"properties" : 
			[
				{
					"name" : "HELPSTRING",
					"value" : "Value Computed by CMake"
				}
			],
			"type" : "STATIC",
			"value" : "/Users/lalalalz/CLionProjects/algorithm/DP_1149"
		},
		{
			"name" : "DP_11726_BINARY_DIR",
			"properties" : 
			[
				{
					"name" : "HELPSTRING",
					"value" : "Value Computed by CMake"
				}
			],
			"type" : "STATIC",
			"value" : "/Users/lalalalz/CLionProjects/algorithm/cmake-build-debug/DP_11726"
		},
		{
			"name" : "DP_11726_IS_TOP_LEVEL",
			"properties" : 
			[
				{
					"name" : "HELPSTRING",
					"value" : "Value Computed by CMake"
				}
			],
			"type" : "STATIC",
			"value" : "OFF"
		},
		{
			"name" : "DP_11726_SOURCE_DIR",
			"properties" : 
			[
				{
					"name" : "HELPSTRING",
					"value" : "Value Computed by CMake"
				}
			],
			"type" : "STATIC",
			"value" : "/Users/lalalalz/CLionProjects/algorithm/DP_11726"
		},
		{
			"name" : "DP_1256_BINARY_DIR",
			"properties" : 
			[
				{
					"name" : "HELPSTRING",
					"value" : "Value Computed by CMake"
				}
			],
			"type" : "STATIC",
			"value" : "/Users/lalalalz/CLionProjects/algorithm/cmake-build-debug/DP_1256"
		},
		{
			"name" : "DP_1256_IS_TOP_LEVEL",
			"properties" : 
			[
				{
					"name" : "HELPSTRING",
					"value" : "Value Computed by CMake"
				}
			],
			"type" : "STATIC",
			"value" : "OFF"
		},
		{
			"name" : "DP_1256_SOURCE_DIR",
			"properties" : 
			[
				{
					"name" : "HELPSTRING",
					"value" : "Value Computed by CMake"
				}
			],
			"type" : "STATIC",
			"value" : "/Users/lalalalz/CLionProjects/algorithm/DP_1256"
		},
		{
			"name" : "DP_1463_BINARY_DIR",
			"properties" : 
			[
				{
					"name" : "HELPSTRING",
					"value" : "Value Computed by CMake"
				}
			],
			"type" : "STATIC",
			"value" : "/Users/lalalalz/CLionProjects/algorithm/cmake-build-debug/DP_1463"
		},
		{
			"name" : "DP_1463_IS_TOP_LEVEL",
			"properties" : 
			[
				{
					"name" : "HELPSTRING",
					"value" : "Value Computed by CMake"
				}
			],
			"type" : "STATIC",
			"value" : "OFF"
		},
		{
			"name" : "DP_1463_SOURCE_DIR",
			"properties" : 
			[
				{
					"name" : "HELPSTRING",
					"value" : "Value Computed by CMake"
				}
			],
			"type" : "STATIC",
			"value" : "/Users/lalalalz/CLionProjects/algorithm/DP_1463"
		},
		{
			"name" : "DP_1699_BINARY_DIR",
			"properties" : 
			[
				{
					"name" : "HELPSTRING",
					"value" : "Value Computed by CMake"
				}
			],
			"type" : "STATIC",
			"value" : "/Users/lalalalz/CLionProjects/algorithm/cmake-build-debug/DP_1699"
		},
		{
			"name" : "DP_1699_IS_TOP_LEVEL",
			"properties" : 
			[
				{
					"name" : "HELPSTRING",
					"value" : "Value Computed by CMake"
				}
			],
			"type" : "STATIC",
			"value" : "OFF"
		},
		{
			"name" : "DP_1699_SOURCE_DIR",
			"properties" : 
			[
				{
					"name" : "HELPSTRING",
					"value" : "Value Computed by CMake"
				}
			],
			"type" : "STATIC",
			"value" : "/Users/lalalalz/CLionProjects/algorithm/DP_1699"
		},
		{
			"name" : "DP_1904_BINARY_DIR",
			"properties" : 
			[
				{
					"name" : "HELPSTRING",
					"value" : "Value Computed by CMake"
				}
			],
			"type" : "STATIC",
			"value" : "/Users/lalalalz/CLionProjects/algorithm/cmake-build-debug/DP_1904"
		},
		{
			"name" : "DP_1904_IS_TOP_LEVEL",
			"properties" : 
			[
				{
					"name" : "HELPSTRING",
					"value" : "Value Computed by CMake"
				}
			],
			"type" : "STATIC",
			"value" : "OFF"
		},
		{
			"name" : "DP_1904_SOURCE_DIR",
			"properties" : 
			[
				{
					"name" : "HELPSTRING",
					"value" : "Value Computed by CMake"
				}
			],
			"type" : "STATIC",
			"value" : "/Users/lalalalz/CLionProjects/algorithm/DP_1904"
		},
		{
			"name" : "DP_1912_BINARY_DIR",
			"properties" : 
			[
				{
					"name" : "HELPSTRING",
					"value" : "Value Computed by CMake"
				}
			],
			"type" : "STATIC",
			"value" : "/Users/lalalalz/CLionProjects/algorithm/cmake-build-debug/DP_1912"
		},
		{
			"name" : "DP_1912_IS_TOP_LEVEL",
			"properties" : 
			[
				{
					"name" : "HELPSTRING",
					"value" : "Value Computed by CMake"
				}
			],
			"type" : "STATIC",
			"value" : "OFF"
		},
		{
			"name" : "DP_1912_SOURCE_DIR",
			"properties" : 
			[
				{
					"name" : "HELPSTRING",
					"value" : "Value Computed by CMake"
				}
			],
			"type" : "STATIC",
			"value" : "/Users/lalalalz/CLionProjects/algorithm/DP_1912"
		},
		{
			"name" : "DP_1932_BINARY_DIR",
			"properties" : 
			[
				{
					"name" : "HELPSTRING",
					"value" : "Value Computed by CMake"
				}
			],
			"type" : "STATIC",
			"value" : "/Users/lalalalz/CLionProjects/algorithm/cmake-build-debug/DP_1932"
		},
		{
			"name" : "DP_1932_IS_TOP_LEVEL",
			"properties" : 
			[
				{
					"name" : "HELPSTRING",
					"value" : "Value Computed by CMake"
				}
			],
			"type" : "STATIC",
			"value" : "OFF"
		},
		{
			"name" : "DP_1932_SOURCE_DIR",
			"properties" : 
			[
				{
					"name" : "HELPSTRING",
					"value" : "Value Computed by CMake"
				}
			],
			"type" : "STATIC",
			"value" : "/Users/lalalalz/CLionProjects/algorithm/DP_1932"
		},
		{
			"name" : "DP_2193_BINARY_DIR",
			"properties" : 
			[
				{
					"name" : "HELPSTRING",
					"value" : "Value Computed by CMake"
				}
			],
			"type" : "STATIC",
			"value" : "/Users/lalalalz/CLionProjects/algorithm/cmake-build-debug/DP_2193"
		},
		{
			"name" : "DP_2193_IS_TOP_LEVEL",
			"properties" : 
			[
				{
					"name" : "HELPSTRING",
					"value" : "Value Computed by CMake"
				}
			],
			"type" : "STATIC",
			"value" : "OFF"
		},
		{
			"name" : "DP_2193_SOURCE_DIR",
			"properties" : 
			[
				{
					"name" : "HELPSTRING",
					"value" : "Value Computed by CMake"
				}
			],
			"type" : "STATIC",
			"value" : "/Users/lalalalz/CLionProjects/algorithm/DP_2193"
		},
		{
			"name" : "DP_2293_BINARY_DIR",
			"properties" : 
			[
				{
					"name" : "HELPSTRING",
					"value" : "Value Computed by CMake"
				}
			],
			"type" : "STATIC",
			"value" : "/Users/lalalalz/CLionProjects/algorithm/cmake-build-debug/DP_2293"
		},
		{
			"name" : "DP_2293_IS_TOP_LEVEL",
			"properties" : 
			[
				{
					"name" : "HELPSTRING",
					"value" : "Value Computed by CMake"
				}
			],
			"type" : "STATIC",
			"value" : "OFF"
		},
		{
			"name" : "DP_2293_SOURCE_DIR",
			"properties" : 
			[
				{
					"name" : "HELPSTRING",
					"value" : "Value Computed by CMake"
				}
			],
			"type" : "STATIC",
			"value" : "/Users/lalalalz/CLionProjects/algorithm/DP_2293"
		},
		{
			"name" : "DP_2579_BINARY_DIR",
			"properties" : 
			[
				{
					"name" : "HELPSTRING",
					"value" : "Value Computed by CMake"
				}
			],
			"type" : "STATIC",
			"value" : "/Users/lalalalz/CLionProjects/algorithm/cmake-build-debug/DP_2579"
		},
		{
			"name" : "DP_2579_IS_TOP_LEVEL",
			"properties" : 
			[
				{
					"name" : "HELPSTRING",
					"value" : "Value Computed by CMake"
				}
			],
			"type" : "STATIC",
			"value" : "OFF"
		},
		{
			"name" : "DP_2579_SOURCE_DIR",
			"properties" : 
			[
				{
					"name" : "HELPSTRING",
					"value" : "Value Computed by CMake"
				}
			],
			"type" : "STATIC",
			"value" : "/Users/lalalalz/CLionProjects/algorithm/DP_2579"
		},
		{
			"name" : "DP_2839_BINARY_DIR",
			"properties" : 
			[
				{
					"name" : "HELPSTRING",
					"value" : "Value Computed by CMake"
				}
			],
			"type" : "STATIC",
			"value" : "/Users/lalalalz/CLionProjects/algorithm/cmake-build-debug/DP_2839"
		},
		{
			"name" : "DP_2839_IS_TOP_LEVEL",
			"properties" : 
			[
				{
					"name" : "HELPSTRING",
					"value" : "Value Computed by CMake"
				}
			],
			"type" : "STATIC",
			"value" : "OFF"
		},
		{
			"name" : "DP_2839_SOURCE_DIR",
			"properties" : 
			[
				{
					"name" : "HELPSTRING",
					"value" : "Value Computed by CMake"
				}
			],
			"type" : "STATIC",
			"value" : "/Users/lalalalz/CLionProjects/algorithm/DP_2839"
		},
		{
			"name" : "DP_2839_설탕배달_BINARY_DIR",
			"properties" : 
			[
				{
					"name" : "HELPSTRING",
					"value" : "Value Computed by CMake"
				}
			],
			"type" : "STATIC",
			"value" : "/Users/lalalalz/CLionProjects/algorithm/cmake-build-debug/DP_2839_설탕배달"
		},
		{
			"name" : "DP_2839_설탕배달_IS_TOP_LEVEL",
			"properties" : 
			[
				{
					"name" : "HELPSTRING",
					"value" : "Value Computed by CMake"
				}
			],
			"type" : "STATIC",
			"value" : "OFF"
		},
		{
			"name" : "DP_2839_설탕배달_SOURCE_DIR",
			"properties" : 
			[
				{
					"name" : "HELPSTRING",
					"value" : "Value Computed by CMake"
				}
			],
			"type" : "STATIC",
			"value" : "/Users/lalalalz/CLionProjects/algorithm/DP_2839_설탕배달"
		},
		{
			"name" : "DP_9095_BINARY_DIR",
			"properties" : 
			[
				{
					"name" : "HELPSTRING",
					"value" : "Value Computed by CMake"
				}
			],
			"type" : "STATIC",
			"value" : "/Users/lalalalz/CLionProjects/algorithm/cmake-build-debug/DP_9095"
		},
		{
			"name" : "DP_9095_IS_TOP_LEVEL",
			"properties" : 
			[
				{
					"name" : "HELPSTRING",
					"value" : "Value Computed by CMake"
				}
			],
			"type" : "STATIC",
			"value" : "OFF"
		},
		{
			"name" : "DP_9095_SOURCE_DIR",
			"properties" : 
			[
				{
					"name" : "HELPSTRING",
					"value" : "Value Computed by CMake"
				}
			],
			"type" : "STATIC",
			"value" : "/Users/lalalalz/CLionProjects/algorithm/DP_9095"
		},
		{
			"name" : "DP_9465_BINARY_DIR",
			"properties" : 
			[
				{
					"name" : "HELPSTRING",
					"value" : "Value Computed by CMake"
				}
			],
			"type" : "STATIC",
			"value" : "/Users/lalalalz/CLionProjects/algorithm/cmake-build-debug/DP_9465"
		},
		{
			"name" : "DP_9465_IS_TOP_LEVEL",
			"properties" : 
			[
				{
					"name" : "HELPSTRING",
					"value" : "Value Computed by CMake"
				}
			],
			"type" : "STATIC",
			"value" : "OFF"
		},
		{
			"name" : "DP_9465_SOURCE_DIR",
			"properties" : 
			[
				{
					"name" : "HELPSTRING",
					"value" : "Value Computed by CMake"
				}
			],
			"type" : "STATIC",
			"value" : "/Users/lalalalz/CLionProjects/algorithm/DP_9465"
		},
		{
			"name" : "KAKAO_RankingSearch_BINARY_DIR",
			"properties" : 
			[
				{
					"name" : "HELPSTRING",
					"value" : "Value Computed by CMake"
				}
			],
			"type" : "STATIC",
			"value" : "/Users/lalalalz/CLionProjects/algorithm/cmake-build-debug/KAKAO_RankingSearch"
		},
		{
			"name" : "KAKAO_RankingSearch_IS_TOP_LEVEL",
			"properties" : 
			[
				{
					"name" : "HELPSTRING",
					"value" : "Value Computed by CMake"
				}
			],
			"type" : "STATIC",
			"value" : "OFF"
		},
		{
			"name" : "KAKAO_RankingSearch_SOURCE_DIR",
			"properties" : 
			[
				{
					"name" : "HELPSTRING",
					"value" : "Value Computed by CMake"
				}
			],
			"type" : "STATIC",
			"value" : "/Users/lalalalz/CLionProjects/algorithm/KAKAO_RankingSearch"
		},
		{
			"name" : "KAKAO_StringCompression_BINARY_DIR",
			"properties" : 
			[
				{
					"name" : "HELPSTRING",
					"value" : "Value Computed by CMake"
				}
			],
			"type" : "STATIC",
			"value" : "/Users/lalalalz/CLionProjects/algorithm/cmake-build-debug/KAKAO_StringCompression"
		},
		{
			"name" : "KAKAO_StringCompression_IS_TOP_LEVEL",
			"properties" : 
			[
				{
					"name" : "HELPSTRING",
					"value" : "Value Computed by CMake"
				}
			],
			"type" : "STATIC",
			"value" : "OFF"
		},
		{
			"name" : "KAKAO_StringCompression_SOURCE_DIR",
			"properties" : 
			[
				{
					"name" : "HELPSTRING",
					"value" : "Value Computed by CMake"
				}
			],
			"type" : "STATIC",
			"value" : "/Users/lalalalz/CLionProjects/algorithm/KAKAO_StringCompression"
		},
		{
			"name" : "KAKAO_archery_BINARY_DIR",
			"properties" : 
			[
				{
					"name" : "HELPSTRING",
					"value" : "Value Computed by CMake"
				}
			],
			"type" : "STATIC",
			"value" : "/Users/lalalalz/CLionProjects/algorithm/cmake-build-debug/KAKAO_archery"
		},
		{
			"name" : "KAKAO_archery_IS_TOP_LEVEL",
			"properties" : 
			[
				{
					"name" : "HELPSTRING",
					"value" : "Value Computed by CMake"
				}
			],
			"type" : "STATIC",
			"value" : "OFF"
		},
		{
			"name" : "KAKAO_archery_SOURCE_DIR",
			"properties" : 
			[
				{
					"name" : "HELPSTRING",
					"value" : "Value Computed by CMake"
				}
			],
			"type" : "STATIC",
			"value" : "/Users/lalalalz/CLionProjects/algorithm/KAKAO_archery"
		},
		{
			"name" : "KAKAO_bestalbum_BINARY_DIR",
			"properties" : 
			[
				{
					"name" : "HELPSTRING",
					"value" : "Value Computed by CMake"
				}
			],
			"type" : "STATIC",
			"value" : "/Users/lalalalz/CLionProjects/algorithm/cmake-build-debug/KAKAO_bestalbum"
		},
		{
			"name" : "KAKAO_bestalbum_IS_TOP_LEVEL",
			"properties" : 
			[
				{
					"name" : "HELPSTRING",
					"value" : "Value Computed by CMake"
				}
			],
			"type" : "STATIC",
			"value" : "OFF"
		},
		{
			"name" : "KAKAO_bestalbum_SOURCE_DIR",
			"properties" : 
			[
				{
					"name" : "HELPSTRING",
					"value" : "Value Computed by CMake"
				}
			],
			"type" : "STATIC",
			"value" : "/Users/lalalalz/CLionProjects/algorithm/KAKAO_bestalbum"
		},
		{
			"name" : "KAKAO_bracket_BINARY_DIR",
			"properties" : 
			[
				{
					"name" : "HELPSTRING",
					"value" : "Value Computed by CMake"
				}
			],
			"type" : "STATIC",
			"value" : "/Users/lalalalz/CLionProjects/algorithm/cmake-build-debug/KAKAO_bracket"
		},
		{
			"name" : "KAKAO_bracket_IS_TOP_LEVEL",
			"properties" : 
			[
				{
					"name" : "HELPSTRING",
					"value" : "Value Computed by CMake"
				}
			],
			"type" : "STATIC",
			"value" : "OFF"
		},
		{
			"name" : "KAKAO_bracket_SOURCE_DIR",
			"properties" : 
			[
				{
					"name" : "HELPSTRING",
					"value" : "Value Computed by CMake"
				}
			],
			"type" : "STATIC",
			"value" : "/Users/lalalalz/CLionProjects/algorithm/KAKAO_bracket"
		},
		{
			"name" : "KAKAO_cache_BINARY_DIR",
			"properties" : 
			[
				{
					"name" : "HELPSTRING",
					"value" : "Value Computed by CMake"
				}
			],
			"type" : "STATIC",
			"value" : "/Users/lalalalz/CLionProjects/algorithm/cmake-build-debug/KAKAO_cache"
		},
		{
			"name" : "KAKAO_cache_IS_TOP_LEVEL",
			"properties" : 
			[
				{
					"name" : "HELPSTRING",
					"value" : "Value Computed by CMake"
				}
			],
			"type" : "STATIC",
			"value" : "OFF"
		},
		{
			"name" : "KAKAO_cache_SOURCE_DIR",
			"properties" : 
			[
				{
					"name" : "HELPSTRING",
					"value" : "Value Computed by CMake"
				}
			],
			"type" : "STATIC",
			"value" : "/Users/lalalalz/CLionProjects/algorithm/KAKAO_cache"
		},
		{
			"name" : "KAKAO_carpet_BINARY_DIR",
			"properties" : 
			[
				{
					"name" : "HELPSTRING",
					"value" : "Value Computed by CMake"
				}
			],
			"type" : "STATIC",
			"value" : "/Users/lalalalz/CLionProjects/algorithm/cmake-build-debug/KAKAO_carpet"
		},
		{
			"name" : "KAKAO_carpet_IS_TOP_LEVEL",
			"properties" : 
			[
				{
					"name" : "HELPSTRING",
					"value" : "Value Computed by CMake"
				}
			],
			"type" : "STATIC",
			"value" : "OFF"
		},
		{
			"name" : "KAKAO_carpet_SOURCE_DIR",
			"properties" : 
			[
				{
					"name" : "HELPSTRING",
					"value" : "Value Computed by CMake"
				}
			],
			"type" : "STATIC",
			"value" : "/Users/lalalalz/CLionProjects/algorithm/KAKAO_carpet"
		},
		{
			"name" : "KAKAO_compress_BINARY_DIR",
			"properties" : 
			[
				{
					"name" : "HELPSTRING",
					"value" : "Value Computed by CMake"
				}
			],
			"type" : "STATIC",
			"value" : "/Users/lalalalz/CLionProjects/algorithm/cmake-build-debug/KAKAO_compress"
		},
		{
			"name" : "KAKAO_compress_IS_TOP_LEVEL",
			"properties" : 
			[
				{
					"name" : "HELPSTRING",
					"value" : "Value Computed by CMake"
				}
			],
			"type" : "STATIC",
			"value" : "OFF"
		},
		{
			"name" : "KAKAO_compress_SOURCE_DIR",
			"properties" : 
			[
				{
					"name" : "HELPSTRING",
					"value" : "Value Computed by CMake"
				}
			],
			"type" : "STATIC",
			"value" : "/Users/lalalalz/CLionProjects/algorithm/KAKAO_compress"
		},
		{
			"name" : "KAKAO_covid_BINARY_DIR",
			"properties" : 
			[
				{
					"name" : "HELPSTRING",
					"value" : "Value Computed by CMake"
				}
			],
			"type" : "STATIC",
			"value" : "/Users/lalalalz/CLionProjects/algorithm/cmake-build-debug/KAKAO_covid"
		},
		{
			"name" : "KAKAO_covid_IS_TOP_LEVEL",
			"properties" : 
			[
				{
					"name" : "HELPSTRING",
					"value" : "Value Computed by CMake"
				}
			],
			"type" : "STATIC",
			"value" : "OFF"
		},
		{
			"name" : "KAKAO_covid_SOURCE_DIR",
			"properties" : 
			[
				{
					"name" : "HELPSTRING",
					"value" : "Value Computed by CMake"
				}
			],
			"type" : "STATIC",
			"value" : "/Users/lalalalz/CLionProjects/algorithm/KAKAO_covid"
		},
		{
			"name" : "KAKAO_dart_BINARY_DIR",
			"properties" : 
			[
				{
					"name" : "HELPSTRING",
					"value" : "Value Computed by CMake"
				}
			],
			"type" : "STATIC",
			"value" : "/Users/lalalalz/CLionProjects/algorithm/cmake-build-debug/KAKAO_dart"
		},
		{
			"name" : "KAKAO_dart_IS_TOP_LEVEL",
			"properties" : 
			[
				{
					"name" : "HELPSTRING",
					"value" : "Value Computed by CMake"
				}
			],
			"type" : "STATIC",
			"value" : "OFF"
		},
		{
			"name" : "KAKAO_dart_SOURCE_DIR",
			"properties" : 
			[
				{
					"name" : "HELPSTRING",
					"value" : "Value Computed by CMake"
				}
			],
			"type" : "STATIC",
			"value" : "/Users/lalalalz/CLionProjects/algorithm/KAKAO_dart"
		},
		{
			"name" : "KAKAO_fail_BINARY_DIR",
			"properties" : 
			[
				{
					"name" : "HELPSTRING",
					"value" : "Value Computed by CMake"
				}
			],
			"type" : "STATIC",
			"value" : "/Users/lalalalz/CLionProjects/algorithm/cmake-build-debug/KAKAO_fail"
		},
		{
			"name" : "KAKAO_fail_IS_TOP_LEVEL",
			"properties" : 
			[
				{
					"name" : "HELPSTRING",
					"value" : "Value Computed by CMake"
				}
			],
			"type" : "STATIC",
			"value" : "OFF"
		},
		{
			"name" : "KAKAO_fail_SOURCE_DIR",
			"properties" : 
			[
				{
					"name" : "HELPSTRING",
					"value" : "Value Computed by CMake"
				}
			],
			"type" : "STATIC",
			"value" : "/Users/lalalalz/CLionProjects/algorithm/KAKAO_fail"
		},
		{
			"name" : "KAKAO_fileSort_BINARY_DIR",
			"properties" : 
			[
				{
					"name" : "HELPSTRING",
					"value" : "Value Computed by CMake"
				}
			],
			"type" : "STATIC",
			"value" : "/Users/lalalalz/CLionProjects/algorithm/cmake-build-debug/KAKAO_fileSort"
		},
		{
			"name" : "KAKAO_fileSort_IS_TOP_LEVEL",
			"properties" : 
			[
				{
					"name" : "HELPSTRING",
					"value" : "Value Computed by CMake"
				}
			],
			"type" : "STATIC",
			"value" : "OFF"
		},
		{
			"name" : "KAKAO_fileSort_SOURCE_DIR",
			"properties" : 
			[
				{
					"name" : "HELPSTRING",
					"value" : "Value Computed by CMake"
				}
			],
			"type" : "STATIC",
			"value" : "/Users/lalalalz/CLionProjects/algorithm/KAKAO_fileSort"
		},
		{
			"name" : "KAKAO_findingPrimeNumber_BINARY_DIR",
			"properties" : 
			[
				{
					"name" : "HELPSTRING",
					"value" : "Value Computed by CMake"
				}
			],
			"type" : "STATIC",
			"value" : "/Users/lalalalz/CLionProjects/algorithm/cmake-build-debug/KAKAO_findingPrimeNumber"
		},
		{
			"name" : "KAKAO_findingPrimeNumber_IS_TOP_LEVEL",
			"properties" : 
			[
				{
					"name" : "HELPSTRING",
					"value" : "Value Computed by CMake"
				}
			],
			"type" : "STATIC",
			"value" : "OFF"
		},
		{
			"name" : "KAKAO_findingPrimeNumber_SOURCE_DIR",
			"properties" : 
			[
				{
					"name" : "HELPSTRING",
					"value" : "Value Computed by CMake"
				}
			],
			"type" : "STATIC",
			"value" : "/Users/lalalalz/CLionProjects/algorithm/KAKAO_findingPrimeNumber"
		},
		{
			"name" : "KAKAO_kNumber_BINARY_DIR",
			"properties" : 
			[
				{
					"name" : "HELPSTRING",
					"value" : "Value Computed by CMake"
				}
			],
			"type" : "STATIC",
			"value" : "/Users/lalalalz/CLionProjects/algorithm/cmake-build-debug/KAKAO_kNumber"
		},
		{
			"name" : "KAKAO_kNumber_IS_TOP_LEVEL",
			"properties" : 
			[
				{
					"name" : "HELPSTRING",
					"value" : "Value Computed by CMake"
				}
			],
			"type" : "STATIC",
			"value" : "OFF"
		},
		{
			"name" : "KAKAO_kNumber_SOURCE_DIR",
			"properties" : 
			[
				{
					"name" : "HELPSTRING",
					"value" : "Value Computed by CMake"
				}
			],
			"type" : "STATIC",
			"value" : "/Users/lalalalz/CLionProjects/algorithm/KAKAO_kNumber"
		},
		{
			"name" : "KAKAO_keypad_BINARY_DIR",
			"properties" : 
			[
				{
					"name" : "HELPSTRING",
					"value" : "Value Computed by CMake"
				}
			],
			"type" : "STATIC",
			"value" : "/Users/lalalalz/CLionProjects/algorithm/cmake-build-debug/KAKAO_keypad"
		},
		{
			"name" : "KAKAO_keypad_IS_TOP_LEVEL",
			"properties" : 
			[
				{
					"name" : "HELPSTRING",
					"value" : "Value Computed by CMake"
				}
			],
			"type" : "STATIC",
			"value" : "OFF"
		},
		{
			"name" : "KAKAO_keypad_SOURCE_DIR",
			"properties" : 
			[
				{
					"name" : "HELPSTRING",
					"value" : "Value Computed by CMake"
				}
			],
			"type" : "STATIC",
			"value" : "/Users/lalalalz/CLionProjects/algorithm/KAKAO_keypad"
		},
		{
			"name" : "KAKAO_lockAndKey_BINARY_DIR",
			"properties" : 
			[
				{
					"name" : "HELPSTRING",
					"value" : "Value Computed by CMake"
				}
			],
			"type" : "STATIC",
			"value" : "/Users/lalalalz/CLionProjects/algorithm/cmake-build-debug/KAKAO_lockAndKey"
		},
		{
			"name" : "KAKAO_lockAndKey_IS_TOP_LEVEL",
			"properties" : 
			[
				{
					"name" : "HELPSTRING",
					"value" : "Value Computed by CMake"
				}
			],
			"type" : "STATIC",
			"value" : "OFF"
		},
		{
			"name" : "KAKAO_lockAndKey_SOURCE_DIR",
			"properties" : 
			[
				{
					"name" : "HELPSTRING",
					"value" : "Value Computed by CMake"
				}
			],
			"type" : "STATIC",
			"value" : "/Users/lalalalz/CLionProjects/algorithm/KAKAO_lockAndKey"
		},
		{
			"name" : "KAKAO_lotto_BINARY_DIR",
			"properties" : 
			[
				{
					"name" : "HELPSTRING",
					"value" : "Value Computed by CMake"
				}
			],
			"type" : "STATIC",
			"value" : "/Users/lalalalz/CLionProjects/algorithm/cmake-build-debug/KAKAO_lotto"
		},
		{
			"name" : "KAKAO_lotto_IS_TOP_LEVEL",
			"properties" : 
			[
				{
					"name" : "HELPSTRING",
					"value" : "Value Computed by CMake"
				}
			],
			"type" : "STATIC",
			"value" : "OFF"
		},
		{
			"name" : "KAKAO_lotto_SOURCE_DIR",
			"properties" : 
			[
				{
					"name" : "HELPSTRING",
					"value" : "Value Computed by CMake"
				}
			],
			"type" : "STATIC",
			"value" : "/Users/lalalalz/CLionProjects/algorithm/KAKAO_lotto"
		},
		{
			"name" : "KAKAO_menuRenewal_BINARY_DIR",
			"properties" : 
			[
				{
					"name" : "HELPSTRING",
					"value" : "Value Computed by CMake"
				}
			],
			"type" : "STATIC",
			"value" : "/Users/lalalalz/CLionProjects/algorithm/cmake-build-debug/KAKAO_menuRenewal"
		},
		{
			"name" : "KAKAO_menuRenewal_IS_TOP_LEVEL",
			"properties" : 
			[
				{
					"name" : "HELPSTRING",
					"value" : "Value Computed by CMake"
				}
			],
			"type" : "STATIC",
			"value" : "OFF"
		},
		{
			"name" : "KAKAO_menuRenewal_SOURCE_DIR",
			"properties" : 
			[
				{
					"name" : "HELPSTRING",
					"value" : "Value Computed by CMake"
				}
			],
			"type" : "STATIC",
			"value" : "/Users/lalalalz/CLionProjects/algorithm/KAKAO_menuRenewal"
		},
		{
			"name" : "KAKAO_newID_BINARY_DIR",
			"properties" : 
			[
				{
					"name" : "HELPSTRING",
					"value" : "Value Computed by CMake"
				}
			],
			"type" : "STATIC",
			"value" : "/Users/lalalalz/CLionProjects/algorithm/cmake-build-debug/KAKAO_newID"
		},
		{
			"name" : "KAKAO_newID_IS_TOP_LEVEL",
			"properties" : 
			[
				{
					"name" : "HELPSTRING",
					"value" : "Value Computed by CMake"
				}
			],
			"type" : "STATIC",
			"value" : "OFF"
		},
		{
			"name" : "KAKAO_newID_SOURCE_DIR",
			"properties" : 
			[
				{
					"name" : "HELPSTRING",
					"value" : "Value Computed by CMake"
				}
			],
			"type" : "STATIC",
			"value" : "/Users/lalalalz/CLionProjects/algorithm/KAKAO_newID"
		},
		{
			"name" : "KAKAO_newsClustering_BINARY_DIR",
			"properties" : 
			[
				{
					"name" : "HELPSTRING",
					"value" : "Value Computed by CMake"
				}
			],
			"type" : "STATIC",
			"value" : "/Users/lalalalz/CLionProjects/algorithm/cmake-build-debug/KAKAO_newsClustering"
		},
		{
			"name" : "KAKAO_newsClustering_IS_TOP_LEVEL",
			"properties" : 
			[
				{
					"name" : "HELPSTRING",
					"value" : "Value Computed by CMake"
				}
			],
			"type" : "STATIC",
			"value" : "OFF"
		},
		{
			"name" : "KAKAO_newsClustering_SOURCE_DIR",
			"properties" : 
			[
				{
					"name" : "HELPSTRING",
					"value" : "Value Computed by CMake"
				}
			],
			"type" : "STATIC",
			"value" : "/Users/lalalalz/CLionProjects/algorithm/KAKAO_newsClustering"
		},
		{
			"name" : "KAKAO_nickname_BINARY_DIR",
			"properties" : 
			[
				{
					"name" : "HELPSTRING",
					"value" : "Value Computed by CMake"
				}
			],
			"type" : "STATIC",
			"value" : "/Users/lalalalz/CLionProjects/algorithm/cmake-build-debug/KAKAO_nickname"
		},
		{
			"name" : "KAKAO_nickname_IS_TOP_LEVEL",
			"properties" : 
			[
				{
					"name" : "HELPSTRING",
					"value" : "Value Computed by CMake"
				}
			],
			"type" : "STATIC",
			"value" : "OFF"
		},
		{
			"name" : "KAKAO_nickname_SOURCE_DIR",
			"properties" : 
			[
				{
					"name" : "HELPSTRING",
					"value" : "Value Computed by CMake"
				}
			],
			"type" : "STATIC",
			"value" : "/Users/lalalalz/CLionProjects/algorithm/KAKAO_nickname"
		},
		{
			"name" : "KAKAO_parkingFees_BINARY_DIR",
			"properties" : 
			[
				{
					"name" : "HELPSTRING",
					"value" : "Value Computed by CMake"
				}
			],
			"type" : "STATIC",
			"value" : "/Users/lalalalz/CLionProjects/algorithm/cmake-build-debug/KAKAO_parkingFees"
		},
		{
			"name" : "KAKAO_parkingFees_IS_TOP_LEVEL",
			"properties" : 
			[
				{
					"name" : "HELPSTRING",
					"value" : "Value Computed by CMake"
				}
			],
			"type" : "STATIC",
			"value" : "OFF"
		},
		{
			"name" : "KAKAO_parkingFees_SOURCE_DIR",
			"properties" : 
			[
				{
					"name" : "HELPSTRING",
					"value" : "Value Computed by CMake"
				}
			],
			"type" : "STATIC",
			"value" : "/Users/lalalalz/CLionProjects/algorithm/KAKAO_parkingFees"
		},
		{
			"name" : "KAKAO_photo_BINARY_DIR",
			"properties" : 
			[
				{
					"name" : "HELPSTRING",
					"value" : "Value Computed by CMake"
				}
			],
			"type" : "STATIC",
			"value" : "/Users/lalalalz/CLionProjects/algorithm/cmake-build-debug/KAKAO_photo"
		},
		{
			"name" : "KAKAO_photo_IS_TOP_LEVEL",
			"properties" : 
			[
				{
					"name" : "HELPSTRING",
					"value" : "Value Computed by CMake"
				}
			],
			"type" : "STATIC",
			"value" : "OFF"
		},
		{
			"name" : "KAKAO_photo_SOURCE_DIR",
			"properties" : 
			[
				{
					"name" : "HELPSTRING",
					"value" : "Value Computed by CMake"
				}
			],
			"type" : "STATIC",
			"value" : "/Users/lalalalz/CLionProjects/algorithm/KAKAO_photo"
		},
		{
			"name" : "KAKAO_pyramid_BINARY_DIR",
			"properties" : 
			[
				{
					"name" : "HELPSTRING",
					"value" : "Value Computed by CMake"
				}
			],
			"type" : "STATIC",
			"value" : "/Users/lalalalz/CLionProjects/algorithm/cmake-build-debug/KAKAO_pyramid"
		},
		{
			"name" : "KAKAO_pyramid_IS_TOP_LEVEL",
			"properties" : 
			[
				{
					"name" : "HELPSTRING",
					"value" : "Value Computed by CMake"
				}
			],
			"type" : "STATIC",
			"value" : "OFF"
		},
		{
			"name" : "KAKAO_pyramid_SOURCE_DIR",
			"properties" : 
			[
				{
					"name" : "HELPSTRING",
					"value" : "Value Computed by CMake"
				}
			],
			"type" : "STATIC",
			"value" : "/Users/lalalalz/CLionProjects/algorithm/KAKAO_pyramid"
		},
		{
			"name" : "KAKAO_report_BINARY_DIR",
			"properties" : 
			[
				{
					"name" : "HELPSTRING",
					"value" : "Value Computed by CMake"
				}
			],
			"type" : "STATIC",
			"value" : "/Users/lalalalz/CLionProjects/algorithm/cmake-build-debug/KAKAO_report"
		},
		{
			"name" : "KAKAO_report_IS_TOP_LEVEL",
			"properties" : 
			[
				{
					"name" : "HELPSTRING",
					"value" : "Value Computed by CMake"
				}
			],
			"type" : "STATIC",
			"value" : "OFF"
		},
		{
			"name" : "KAKAO_report_SOURCE_DIR",
			"properties" : 
			[
				{
					"name" : "HELPSTRING",
					"value" : "Value Computed by CMake"
				}
			],
			"type" : "STATIC",
			"value" : "/Users/lalalalz/CLionProjects/algorithm/KAKAO_report"
		},
		{
			"name" : "KAKAO_rotation_BINARY_DIR",
			"properties" : 
			[
				{
					"name" : "HELPSTRING",
					"value" : "Value Computed by CMake"
				}
			],
			"type" : "STATIC",
			"value" : "/Users/lalalalz/CLionProjects/algorithm/cmake-build-debug/KAKAO_rotation"
		},
		{
			"name" : "KAKAO_rotation_IS_TOP_LEVEL",
			"properties" : 
			[
				{
					"name" : "HELPSTRING",
					"value" : "Value Computed by CMake"
				}
			],
			"type" : "STATIC",
			"value" : "OFF"
		},
		{
			"name" : "KAKAO_rotation_SOURCE_DIR",
			"properties" : 
			[
				{
					"name" : "HELPSTRING",
					"value" : "Value Computed by CMake"
				}
			],
			"type" : "STATIC",
			"value" : "/Users/lalalalz/CLionProjects/algorithm/KAKAO_rotation"
		},
		{
			"name" : "KAKAO_secretMap_BINARY_DIR",
			"properties" : 
			[
				{
					"name" : "HELPSTRING",
					"value" : "Value Computed by CMake"
				}
			],
			"type" : "STATIC",
			"value" : "/Users/lalalalz/CLionProjects/algorithm/cmake-build-debug/KAKAO_secretMap"
		},
		{
			"name" : "KAKAO_secretMap_IS_TOP_LEVEL",
			"properties" : 
			[
				{
					"name" : "HELPSTRING",
					"value" : "Value Computed by CMake"
				}
			],
			"type" : "STATIC",
			"value" : "OFF"
		},
		{
			"name" : "KAKAO_secretMap_SOURCE_DIR",
			"properties" : 
			[
				{
					"name" : "HELPSTRING",
					"value" : "Value Computed by CMake"
				}
			],
			"type" : "STATIC",
			"value" : "/Users/lalalalz/CLionProjects/algorithm/KAKAO_secretMap"
		},
		{
			"name" : "KAKAO_stringAndWord_BINARY_DIR",
			"properties" : 
			[
				{
					"name" : "HELPSTRING",
					"value" : "Value Computed by CMake"
				}
			],
			"type" : "STATIC",
			"value" : "/Users/lalalalz/CLionProjects/algorithm/cmake-build-debug/KAKAO_stringAndWord"
		},
		{
			"name" : "KAKAO_stringAndWord_IS_TOP_LEVEL",
			"properties" : 
			[
				{
					"name" : "HELPSTRING",
					"value" : "Value Computed by CMake"
				}
			],
			"type" : "STATIC",
			"value" : "OFF"
		},
		{
			"name" : "KAKAO_stringAndWord_SOURCE_DIR",
			"properties" : 
			[
				{
					"name" : "HELPSTRING",
					"value" : "Value Computed by CMake"
				}
			],
			"type" : "STATIC",
			"value" : "/Users/lalalalz/CLionProjects/algorithm/KAKAO_stringAndWord"
		},
		{
			"name" : "KAKAO_taxi_BINARY_DIR",
			"properties" : 
			[
				{
					"name" : "HELPSTRING",
					"value" : "Value Computed by CMake"
				}
			],
			"type" : "STATIC",
			"value" : "/Users/lalalalz/CLionProjects/algorithm/cmake-build-debug/KAKAO_taxi"
		},
		{
			"name" : "KAKAO_taxi_IS_TOP_LEVEL",
			"properties" : 
			[
				{
					"name" : "HELPSTRING",
					"value" : "Value Computed by CMake"
				}
			],
			"type" : "STATIC",
			"value" : "OFF"
		},
		{
			"name" : "KAKAO_taxi_SOURCE_DIR",
			"properties" : 
			[
				{
					"name" : "HELPSTRING",
					"value" : "Value Computed by CMake"
				}
			],
			"type" : "STATIC",
			"value" : "/Users/lalalalz/CLionProjects/algorithm/KAKAO_taxi"
		},
		{
			"name" : "KAKAO_test_BINARY_DIR",
			"properties" : 
			[
				{
					"name" : "HELPSTRING",
					"value" : "Value Computed by CMake"
				}
			],
			"type" : "STATIC",
			"value" : "/Users/lalalalz/CLionProjects/algorithm/cmake-build-debug/KAKAO_test"
		},
		{
			"name" : "KAKAO_test_IS_TOP_LEVEL",
			"properties" : 
			[
				{
					"name" : "HELPSTRING",
					"value" : "Value Computed by CMake"
				}
			],
			"type" : "STATIC",
			"value" : "OFF"
		},
		{
			"name" : "KAKAO_test_SOURCE_DIR",
			"properties" : 
			[
				{
					"name" : "HELPSTRING",
					"value" : "Value Computed by CMake"
				}
			],
			"type" : "STATIC",
			"value" : "/Users/lalalalz/CLionProjects/algorithm/KAKAO_test"
		},
		{
			"name" : "KAKAO_thatSong_BINARY_DIR",
			"properties" : 
			[
				{
					"name" : "HELPSTRING",
					"value" : "Value Computed by CMake"
				}
			],
			"type" : "STATIC",
			"value" : "/Users/lalalalz/CLionProjects/algorithm/cmake-build-debug/KAKAO_thatSong"
		},
		{
			"name" : "KAKAO_thatSong_IS_TOP_LEVEL",
			"properties" : 
			[
				{
					"name" : "HELPSTRING",
					"value" : "Value Computed by CMake"
				}
			],
			"type" : "STATIC",
			"value" : "OFF"
		},
		{
			"name" : "KAKAO_thatSong_SOURCE_DIR",
			"properties" : 
			[
				{
					"name" : "HELPSTRING",
					"value" : "Value Computed by CMake"
				}
			],
			"type" : "STATIC",
			"value" : "/Users/lalalalz/CLionProjects/algorithm/KAKAO_thatSong"
		},
		{
			"name" : "KAKAO_traffic_BINARY_DIR",
			"properties" : 
			[
				{
					"name" : "HELPSTRING",
					"value" : "Value Computed by CMake"
				}
			],
			"type" : "STATIC",
			"value" : "/Users/lalalalz/CLionProjects/algorithm/cmake-build-debug/KAKAO_traffic"
		},
		{
			"name" : "KAKAO_traffic_IS_TOP_LEVEL",
			"properties" : 
			[
				{
					"name" : "HELPSTRING",
					"value" : "Value Computed by CMake"
				}
			],
			"type" : "STATIC",
			"value" : "OFF"
		},
		{
			"name" : "KAKAO_traffic_SOURCE_DIR",
			"properties" : 
			[
				{
					"name" : "HELPSTRING",
					"value" : "Value Computed by CMake"
				}
			],
			"type" : "STATIC",
			"value" : "/Users/lalalalz/CLionProjects/algorithm/KAKAO_traffic"
		},
		{
			"name" : "KAKAO_zip_BINARY_DIR",
			"properties" : 
			[
				{
					"name" : "HELPSTRING",
					"value" : "Value Computed by CMake"
				}
			],
			"type" : "STATIC",
			"value" : "/Users/lalalalz/CLionProjects/algorithm/cmake-build-debug/KAKAO_zip"
		},
		{
			"name" : "KAKAO_zip_IS_TOP_LEVEL",
			"properties" : 
			[
				{
					"name" : "HELPSTRING",
					"value" : "Value Computed by CMake"
				}
			],
			"type" : "STATIC",
			"value" : "OFF"
		},
		{
			"name" : "KAKAO_zip_SOURCE_DIR",
			"properties" : 
			[
				{
					"name" : "HELPSTRING",
					"value" : "Value Computed by CMake"
				}
			],
			"type" : "STATIC",
			"value" : "/Users/lalalalz/CLionProjects/algorithm/KAKAO_zip"
		},
		{
			"name" : "KAKAO_주차요금_BINARY_DIR",
			"properties" : 
			[
				{
					"name" : "HELPSTRING",
					"value" : "Value Computed by CMake"
				}
			],
			"type" : "STATIC",
			"value" : "/Users/lalalalz/CLionProjects/algorithm/cmake-build-debug/KAKAO_주차요금"
		},
		{
			"name" : "KAKAO_주차요금_IS_TOP_LEVEL",
			"properties" : 
			[
				{
					"name" : "HELPSTRING",
					"value" : "Value Computed by CMake"
				}
			],
			"type" : "STATIC",
			"value" : "OFF"
		},
		{
			"name" : "KAKAO_주차요금_SOURCE_DIR",
			"properties" : 
			[
				{
					"name" : "HELPSTRING",
					"value" : "Value Computed by CMake"
				}
			],
			"type" : "STATIC",
			"value" : "/Users/lalalalz/CLionProjects/algorithm/KAKAO_주차요금"
		},
		{
			"name" : "TestA_BINARY_DIR",
			"properties" : 
			[
				{
					"name" : "HELPSTRING",
					"value" : "Value Computed by CMake"
				}
			],
			"type" : "STATIC",
			"value" : "/Users/lalalalz/CLionProjects/algorithm/cmake-build-debug/TestA"
		},
		{
			"name" : "TestA_IS_TOP_LEVEL",
			"properties" : 
			[
				{
					"name" : "HELPSTRING",
					"value" : "Value Computed by CMake"
				}
			],
			"type" : "STATIC",
			"value" : "OFF"
		},
		{
			"name" : "TestA_SOURCE_DIR",
			"properties" : 
			[
				{
					"name" : "HELPSTRING",
					"value" : "Value Computed by CMake"
				}
			],
			"type" : "STATIC",
			"value" : "/Users/lalalalz/CLionProjects/algorithm/TestA"
		},
		{
			"name" : "TestB_BINARY_DIR",
			"properties" : 
			[
				{
					"name" : "HELPSTRING",
					"value" : "Value Computed by CMake"
				}
			],
			"type" : "STATIC",
			"value" : "/Users/lalalalz/CLionProjects/algorithm/cmake-build-debug/TestB"
		},
		{
			"name" : "TestB_IS_TOP_LEVEL",
			"properties" : 
			[
				{
					"name" : "HELPSTRING",
					"value" : "Value Computed by CMake"
				}
			],
			"type" : "STATIC",
			"value" : "OFF"
		},
		{
			"name" : "TestB_SOURCE_DIR",
			"properties" : 
			[
				{
					"name" : "HELPSTRING",
					"value" : "Value Computed by CMake"
				}
			],
			"type" : "STATIC",
			"value" : "/Users/lalalalz/CLionProjects/algorithm/TestB"
		},
		{
			"name" : "algorithm_BINARY_DIR",
			"properties" : 
			[
				{
					"name" : "HELPSTRING",
					"value" : "Value Computed by CMake"
				}
			],
			"type" : "STATIC",
			"value" : "/Users/lalalalz/CLionProjects/algorithm/cmake-build-debug"
		},
		{
			"name" : "algorithm_IS_TOP_LEVEL",
			"properties" : 
			[
				{
					"name" : "HELPSTRING",
					"value" : "Value Computed by CMake"
				}
			],
			"type" : "STATIC",
			"value" : "ON"
		},
		{
			"name" : "algorithm_SOURCE_DIR",
			"properties" : 
			[
				{
					"name" : "HELPSTRING",
					"value" : "Value Computed by CMake"
				}
			],
			"type" : "STATIC",
			"value" : "/Users/lalalalz/CLionProjects/algorithm"
		}
	],
	"kind" : "cache",
	"version" : 
	{
		"major" : 2,
		"minor" : 0
	}
}
